setuptools_pybind11.py
setuptools_pybind11-0.4.0.dist-info/LICENSE
setuptools_pybind11-0.4.0.dist-info/METADATA
setuptools_pybind11-0.4.0.dist-info/WHEEL
setuptools_pybind11-0.4.0.dist-info/top_level.txt
setuptools_pybind11-0.4.0.dist-info/RECORD
